radar/__init__.py
radar/api.py
radar/endpoints.py
radar/errors.py
radar/utils.py
radar/version.py
radar/models/__init__.py
radar/models/address.py
radar/models/context.py
radar/models/event.py
radar/models/geofence.py
radar/models/model.py
radar/models/place.py
radar/models/region.py
radar/models/route.py
radar/models/user.py
radar_python-0.0.4.dist-info/LICENSE
radar_python-0.0.4.dist-info/METADATA
radar_python-0.0.4.dist-info/WHEEL
radar_python-0.0.4.dist-info/top_level.txt
radar_python-0.0.4.dist-info/RECORD
