Metadata-Version: 2.1
Name: radar-python
Version: 0.0.4
Summary: Python bindings for the Radar API
Home-page: https://github.com/radarlabs/radar-python
Author: Radar
Author-email: support@radar.io
License: MIT
Project-URL: Documentation, https://radar.io/documentation/api
Project-URL: Source Code, https://github.com/radarlabs/radar-python
Platform: UNKNOWN
Requires-Python: >=3.4
Requires-Dist: requests (>=2.20)
